pytlai/__init__.py
pytlai/catalog.py
pytlai/cli.py
pytlai/config.py
pytlai/core.py
pytlai/export.py
pytlai/importers.py
pytlai/languages.py
pytlai/py.typed
pytlai/cache/__init__.py
pytlai/cache/base.py
pytlai/cache/file.py
pytlai/cache/memory.py
pytlai/cache/redis.py
pytlai/processors/__init__.py
pytlai/processors/base.py
pytlai/processors/html.py
pytlai/processors/python.py
pytlai/providers/__init__.py
pytlai/providers/base.py
pytlai/providers/openai.py
pytlai-1.0.0.dist-info/METADATA
pytlai-1.0.0.dist-info/WHEEL
pytlai-1.0.0.dist-info/entry_points.txt
pytlai-1.0.0.dist-info/licenses/LICENSE
pytlai-1.0.0.dist-info/RECORD
