Metadata-Version: 2.4
Name: pytlai
Version: 1.0.0
Summary: Python Translation AI - Translate Python scripts or web pages on the fly to any human language
Project-URL: Homepage, https://labs.zaguanai.com/en/experiments/pytlai
Project-URL: Documentation, https://github.com/ZaguanLabs/pytlai#readme
Project-URL: Repository, https://github.com/ZaguanLabs/pytlai
Project-URL: Issues, https://github.com/ZaguanLabs/pytlai/issues
Author: pytlai contributors
License-Expression: MIT
License-File: LICENSE
Keywords: ai,docstrings,gettext,html,i18n,internationalization,localization,openai,python,translation
Classifier: Development Status :: 5 - Production/Stable
Classifier: Intended Audience :: Developers
Classifier: License :: OSI Approved :: MIT License
Classifier: Operating System :: OS Independent
Classifier: Programming Language :: Python :: 3
Classifier: Programming Language :: Python :: 3.10
Classifier: Programming Language :: Python :: 3.11
Classifier: Programming Language :: Python :: 3.12
Classifier: Topic :: Software Development :: Internationalization
Classifier: Topic :: Software Development :: Localization
Classifier: Topic :: Text Processing :: Linguistic
Classifier: Typing :: Typed
Requires-Python: >=3.10
Requires-Dist: beautifulsoup4>=4.12
Requires-Dist: lxml>=5.0
Requires-Dist: openai>=1.0
Provides-Extra: all
Requires-Dist: pyyaml>=6.0; extra == 'all'
Requires-Dist: redis>=5.0; extra == 'all'
Provides-Extra: dev
Requires-Dist: coverage>=7.0; extra == 'dev'
Requires-Dist: mypy>=1.0; extra == 'dev'
Requires-Dist: pytest-asyncio>=0.23; extra == 'dev'
Requires-Dist: pytest>=8.0; extra == 'dev'
Requires-Dist: ruff>=0.1; extra == 'dev'
Provides-Extra: redis
Requires-Dist: redis>=5.0; extra == 'redis'
Provides-Extra: yaml
Requires-Dist: pyyaml>=6.0; extra == 'yaml'
